explorytics/__init__.py
explorytics/core/__init__.py
explorytics/core/analyzer.py
explorytics/utils/helpers.py
explorytics/visualizations/plots.py
explorytics-0.1.5.dist-info/LICENSE
explorytics-0.1.5.dist-info/METADATA
explorytics-0.1.5.dist-info/WHEEL
explorytics-0.1.5.dist-info/top_level.txt
explorytics-0.1.5.dist-info/RECORD
