Metadata-Version: 2.1
Name: explorytics
Version: 0.1.5
Summary: A comprehensive Python library for Exploratory Data Analysis
Home-page: https://github.com/mohitmahajan095/explorytics
Author: Mohit Mahajan
Author-email: mohitmahajan3715@gmail.com
Classifier: Programming Language :: Python :: 3
Classifier: License :: OSI Approved :: MIT License
Classifier: Operating System :: OS Independent
Classifier: Topic :: Scientific/Engineering :: Information Analysis
Classifier: Topic :: Scientific/Engineering :: Visualization
Classifier: Topic :: Software Development :: Libraries :: Python Modules
Requires-Python: >=3.8
License-File: LICENSE
Requires-Dist: pandas>=1.3.0
Requires-Dist: numpy>=1.20.0
Requires-Dist: plotly>=5.0.0
Requires-Dist: scipy>=1.7.0
